wuwaconvene/__init__.py
wuwaconvene/client.py
wuwaconvene/setting.py
wuwaconvene/src/assets/character_icon.json
wuwaconvene/src/assets/frame.png
wuwaconvene/src/assets/line.png
wuwaconvene/src/assets/maska.png
wuwaconvene/src/assets/character/background_five.png
wuwaconvene/src/assets/character/background_four.png
wuwaconvene/src/assets/character/background_three.png
wuwaconvene/src/assets/character/count.png
wuwaconvene/src/assets/character/count_color_line.png
wuwaconvene/src/assets/character/count_line.png
wuwaconvene/src/assets/character/shadow_five.png
wuwaconvene/src/assets/character/shadow_four.png
wuwaconvene/src/assets/character/shadow_three.png
wuwaconvene/src/assets/font/font_hsr.ttf
wuwaconvene/src/assets/stars/five.png
wuwaconvene/src/assets/stars/four.png
wuwaconvene/src/assets/stars/one.png
wuwaconvene/src/assets/stars/three.png
wuwaconvene/src/assets/stars/two.png
wuwaconvene/src/tools/color.py
wuwaconvene/src/tools/generator.py
wuwaconvene/src/tools/json_data.py
wuwaconvene/src/tools/model.py
wuwaconvene/src/tools/pill.py
wuwaconvene/src/tools/uttils.py
wuwaconvene-0.0.2.dist-info/LICENCE
wuwaconvene-0.0.2.dist-info/METADATA
wuwaconvene-0.0.2.dist-info/WHEEL
wuwaconvene-0.0.2.dist-info/top_level.txt
wuwaconvene-0.0.2.dist-info/RECORD
